rpcq/__init__.py
rpcq/_base.py
rpcq/_client.py
rpcq/_server.py
rpcq/_spec.py
rpcq/_utils.py
rpcq/core_messages.py
rpcq/messages.py
rpcq/py.typed
rpcq/version.py
rpcq/external/__init__.py
rpcq/external/dataclasses.py
rpcq-3.0.0.dist-info/LICENSE
rpcq-3.0.0.dist-info/METADATA
rpcq-3.0.0.dist-info/WHEEL
rpcq-3.0.0.dist-info/top_level.txt
rpcq-3.0.0.dist-info/RECORD
