Metadata-Version: 2.1
Name: rpcq
Version: 3.0.0
Summary: The RPC framework and message specification for Rigetti QCS.
Home-page: https://github.com/rigetticomputing/rpcq.git
Author: Rigetti Computing
Author-email: info@rigetti.com
License: Apache-2.0
Keywords: quantum rpc qcs
Platform: UNKNOWN
Requires-Python: >=3.6
Requires-Dist: msgpack (>=0.6)
Requires-Dist: python-rapidjson
Requires-Dist: pyzmq (>=17)
Requires-Dist: ruamel.yaml
